setup.py
Mock/Pinger.py
Mock/__init__.py
Mock/mock.py
Mock/Debugger/MockDebugger.py
Mock/Debugger/PING.py
Mock/Debugger/UnknownDebuggerConfiguration.py
Mock/Debugger/__init__.py
Mock/Debugger/iMockDebugger.py
Mock/Debugger/iMockDebuggerSink.py
Mock/Debugger/Sinks/FileSink.py
Mock/Debugger/Sinks/NullSink.py
Mock/Debugger/Sinks/ServerSink.py
Mock/Debugger/Sinks/__init__.py
PyRQ/__init__.py
PyRQ/version.py
PyRQ.egg-info/PKG-INFO
PyRQ.egg-info/SOURCES.txt
PyRQ.egg-info/dependency_links.txt
PyRQ.egg-info/top_level.txt
PyRQ/Core/__init__.py
PyRQ/Core/Errors/AlreadyStartedError.py
PyRQ/Core/Errors/ClosedError.py
PyRQ/Core/Errors/ConfigurationError.py
PyRQ/Core/Errors/CorruptDataReceived.py
PyRQ/Core/Errors/Finished.py
PyRQ/Core/Errors/LinkageError.py
PyRQ/Core/Errors/LostDataReceived.py
PyRQ/Core/Errors/NoSuchQueue.py
PyRQ/Core/Errors/ProtocolError.py
PyRQ/Core/Errors/PyRQError.py
PyRQ/Core/Errors/QClosedError.py
PyRQ/Core/Errors/StartError.py
PyRQ/Core/Errors/TooManyClientsError.py
PyRQ/Core/Errors/__init__.py
PyRQ/Core/Linkage/Linkage.py
PyRQ/Core/Linkage/__init__.py
PyRQ/Core/Marshal/DefaultMarshaller.py
PyRQ/Core/Marshal/MarshallerFactory.py
PyRQ/Core/Marshal/NoMarshallerError.py
PyRQ/Core/Marshal/OversizedDataError.py
PyRQ/Core/Marshal/UnknownMarshallerError.py
PyRQ/Core/Marshal/__init__.py
PyRQ/Core/Marshal/iMarshaller.py
PyRQ/Core/Messages/ACK.py
PyRQ/Core/Messages/CLOSE.py
PyRQ/Core/Messages/CLOSED.py
PyRQ/Core/Messages/CREATE.py
PyRQ/Core/Messages/DEBUG.py
PyRQ/Core/Messages/GET.py
PyRQ/Core/Messages/GOT.py
PyRQ/Core/Messages/MAXQSIZE.py
PyRQ/Core/Messages/PUT.py
PyRQ/Core/Messages/QSIZE.py
PyRQ/Core/Messages/__init__.py
PyRQ/Core/QueueServer/BootQueueServer.py
PyRQ/Core/QueueServer/QueueServer.py
PyRQ/Core/QueueServer/QueueServerDetails.py
PyRQ/Core/QueueServer/QueueServerHandler.py
PyRQ/Core/QueueServer/QueueServerOptions.py
PyRQ/Core/QueueServer/SubprocessQueueServer.py
PyRQ/Core/QueueServer/__init__.py
PyRQ/Core/QueueServer/iQueueServer.py
PyRQ/Core/QueueServer/iQueueServerDetails.py
PyRQ/Core/QueueWriter/QueueWriter.py
PyRQ/Core/QueueWriter/__init__.py
