Metadata-Version: 1.1
Name: PyRQ
Version: 0.4.0
Summary: A pure Python remote queue (RQ) implementation using the standard Queue api.
Home-page: https://github.com/sys-git/PyRQ
Author: Francis Horsman
Author-email: francis.horsman@gmail.com
License: BSD
Platform: UNKNOWN
Classifier: Development Status :: 4 - Beta
Classifier: Intended Audience :: Developers
Classifier: License :: OSI Approved :: BSD License
Classifier: Operating System :: OS Independent
Classifier: Programming Language :: Python
Classifier: Topic :: Communications
